.flake8
.gitignore
.pylintrc
LICENSE
README.md
environment.yml
setup.py
assets/logo.png
much/Exporter.py
much/Fetcher.py
much/Post.py
much/__init__.py
much/__main__.py
much/util.py
much.egg-info/PKG-INFO
much.egg-info/SOURCES.txt
much.egg-info/dependency_links.txt
much.egg-info/requires.txt
much.egg-info/top_level.txt