Metadata-Version: 2.1
Name: much
Version: 0.0.6
Summary: A simple utility for crawling text from 2ch
Home-page: https://github.com/zeionara/much
Author: Zeio Nara
Author-email: zeionara@gmail.com
License: Apache 2.0
Project-URL: Documentation, https://github.com/zeionara/much#readme
Project-URL: Bug Reports, https://github.com/zeionara/much/issues
Project-URL: Source Code, https://github.com/zeionara/much
Classifier: Intended Audience :: Developers
Classifier: License :: OSI Approved :: Apache Software License
Classifier: Programming Language :: Python :: 3.11
License-File: LICENSE
Requires-Dist: click
Requires-Dist: bs4
Requires-Dist: requests
